noir/__init__.py
noir/__main__.py
noir/client.py
noir/cli/__init__.py
noir/models/__init__.py
noir/models/base.py
noir/models/claude.py
noir/models/claude35.py
noir/models/gpt.py
noir/models/venice.py
noir/models/zai.py
noir/utils/__init__.py
noir/utils/user_agents.py
noir_llm-0.2.6.dist-info/licenses/LICENSE
noir_llm-0.2.6.dist-info/METADATA
noir_llm-0.2.6.dist-info/WHEEL
noir_llm-0.2.6.dist-info/entry_points.txt
noir_llm-0.2.6.dist-info/top_level.txt
noir_llm-0.2.6.dist-info/RECORD
